nose_selenium
